fxpath/__init__.py
fxpath/fxpath.py
fxpath-0.1.3.dist-info/METADATA
fxpath-0.1.3.dist-info/RECORD
fxpath-0.1.3.dist-info/WHEEL
fxpath-0.1.3.dist-info/top_level.txt
