Metadata-Version: 2.1
Name: fxpath
Version: 0.1.3
Summary: search same xpath and inner diff on 2 or more than 2 htmlcontent.
Home-page: https://pypi.org/project/fxpath/
Author: vilame
Author-email: opaquism@hotmail.com
License: MIT
Platform: UNKNOWN
Classifier: Environment :: Web Environment
Classifier: Intended Audience :: Developers
Classifier: Operating System :: OS Independent
